{"tables":[{"header":{"text":"آپ نے فعل ماضی کے ساتھ صیغے سیکھے اور فعل مضارع کے سات صیغے سیکھے اور أمر کے دو۔ ان سب میں سے ایک ایک لفظ کو لیا جاسکتا ہے، یعنی _a_فَعَلَ، _\/a__a_یَفْعَلُ،_\/a_ _a_اِفْعَلْ۔_\/a_ ان تینوں کے ساتھ تین اسم کو یعنی _a_فَاعِل، _\/a__a_مَفْعُول _\/a_اور _a_فِعل _\/a_کو ملایا جائے تو ایک مختصر اور بہترین فارمولا بن جاتا ہے جس کو صرف صغیر کہتے ہیں۔ اگر کسی بھی فعل کا صرف صضیر معلوم ہو تو آپ ان شاء اﷲ باقی سارے صیغے بناسکتے ہیں۔","audioPath":"sabaq_20B_001.mp3"},"rows":[{"arabic":"_a_فَعَلَ_\/a_","secondaryText":"اس نے كيا","isSecondaryTextArabic":false,"audioPath":"sabaq_20B_002.mp3"},{"arabic":"_a_فِعْل_\/a_","secondaryText":"كرنا، كام كا نام","isSecondaryTextArabic":false,"audioPath":"sabaq_20B_007.mp3"},{"arabic":"_a_يَفْعَلُ_\/a_","secondaryText":"وه كرتا هے\/كرےگا","isSecondaryTextArabic":false,"audioPath":"sabaq_20B_003.mp3"},{"arabic":"_a_اِفْعَلْ_\/a_","secondaryText":"كر!","isSecondaryTextArabic":false,"audioPath":"sabaq_20B_004.mp3"},{"arabic":"_a_فَاعِل_\/a_","secondaryText":"كرنے والا","isSecondaryTextArabic":false,"audioPath":"sabaq_20B_005.mp3"},{"arabic":"_a_مَفْعُوْل_\/a_","secondaryText":"جس پر اثر پڑا","isSecondaryTextArabic":false,"audioPath":"sabaq_20B_006.mp3"}]},{"header":{"text":"بَاب فَتَحَ یَفْتَحُ اِفْتَحْ","audioPath":""},"rows":[{"arabic":"_a_فَتَحَ_\/a_","secondaryText":"اس نے كھولا","isSecondaryTextArabic":false,"audioPath":"sabaq_20B_008.mp3"},{"arabic":"_a_يَفْتَحُ_\/a_","secondaryText":"وه كھولتا هے\/كھولے گا","isSecondaryTextArabic":false,"audioPath":"sabaq_20B_009.mp3"},{"arabic":"_a_اِفْتَحْ_\/a_","secondaryText":"كھول!","isSecondaryTextArabic":false,"audioPath":"sabaq_20B_010.mp3"},{"arabic":"_a_فَاتِح_\/a_","secondaryText":"كھولنے والا","isSecondaryTextArabic":false,"audioPath":"sabaq_20B_011.mp3"},{"arabic":"_a_مَفْتُوْح_\/a_","secondaryText":"جس كو كھولا گيا","isSecondaryTextArabic":false,"audioPath":"sabaq_20B_012.mp3"},{"arabic":"_a_فَتْح_\/a_","secondaryText":"كھولنا","isSecondaryTextArabic":false,"audioPath":"sabaq_20B_013.mp3"},{"arabic":"_a_جَعَلَ_\/a_","secondaryText":"اس نے بنایا","isSecondaryTextArabic":false,"audioPath":"sabaq_20B_014.mp3"},{"arabic":"_a_یَجْعَلْ_\/a_","secondaryText":"وہ بناتا ہے\/بنائے گا","isSecondaryTextArabic":false,"audioPath":"sabaq_20B_015.mp3"},{"arabic":"_a_اِجْعَلْ_\/a_","secondaryText":"بنا","isSecondaryTextArabic":false,"audioPath":"sabaq_20B_016.mp3"},{"arabic":"_a_جَاعِل_\/a_","secondaryText":"بنانے والا","isSecondaryTextArabic":false,"audioPath":"sabaq_20B_017.mp3"},{"arabic":"_a_مَجْعُول_\/a_","secondaryText":"جس کو بنایا گیا","isSecondaryTextArabic":false,"audioPath":"sabaq_20B_018.mp3"},{"arabic":"_a_جَعْل_\/a_","secondaryText":"بنانا","isSecondaryTextArabic":false,"audioPath":"sabaq_20B_019.mp3"}]},{"header":{"text":"بَاب نَصَرَ یَنْصُرُ اُنْصُرْ","audioPath":""},"rows":[{"arabic":"_a_نَصَرَ_\/a_","secondaryText":"اس نے مدد کی","isSecondaryTextArabic":false,"audioPath":"sabaq_20B_020.mp3"},{"arabic":"_a_یَنْصُرُ_\/a_","secondaryText":"وہ مدد کرتا ہے\/کرے گا","isSecondaryTextArabic":false,"audioPath":"sabaq_20B_021.mp3"},{"arabic":"_a_اُنْصُرْ_\/a_","secondaryText":"تو مدد کر","isSecondaryTextArabic":false,"audioPath":"sabaq_20B_022.mp3"},{"arabic":"_a_نَاصِر_\/a_","secondaryText":"مدد کرنے والا","isSecondaryTextArabic":false,"audioPath":"sabaq_20B_023.mp3"},{"arabic":"_a_مَنْصُور_\/a_","secondaryText":"جس کی مدد کی گئی","isSecondaryTextArabic":false,"audioPath":"sabaq_20B_024.mp3"},{"arabic":"_a_نَصْر_\/a_","secondaryText":"مدد کرنا","isSecondaryTextArabic":false,"audioPath":"sabaq_20B_025.mp3"},{"arabic":"_a_خَلَقَ_\/a_","secondaryText":"اس نے پیدا کیا","isSecondaryTextArabic":false,"audioPath":"sabaq_20B_026.mp3"},{"arabic":"_a_یَخْلُقُ_\/a_","secondaryText":"وہ پیدا کرتا ہے\/کرے گا","isSecondaryTextArabic":false,"audioPath":"sabaq_20B_027.mp3"},{"arabic":"_a_أُخْلُقْ_\/a_","secondaryText":"پیدا کر","isSecondaryTextArabic":false,"audioPath":"sabaq_20B_028.mp3"},{"arabic":"_a_خَالِق_\/a_","secondaryText":"پیدا کرنے والا","isSecondaryTextArabic":false,"audioPath":"sabaq_20B_029.mp3"},{"arabic":"_a_مَخْلُوق_\/a_","secondaryText":"جس کو پیدا کیا","isSecondaryTextArabic":false,"audioPath":"sabaq_20B_030.mp3"},{"arabic":"_a_خَلْق_\/a_","secondaryText":"پیدا کرنا","isSecondaryTextArabic":false,"audioPath":"sabaq_20B_031.mp3"},{"arabic":"_a_عَبَدَ_\/a_","secondaryText":"اس نے عبادت کی","isSecondaryTextArabic":false,"audioPath":"sabaq_20B_032.mp3"},{"arabic":"_a_یَعْبُدُ_\/a_","secondaryText":"وہ عبادت کرتا ہے\/کرے گا","isSecondaryTextArabic":false,"audioPath":"sabaq_20B_033.mp3"},{"arabic":"_a_اُعْبُدْ_\/a_","secondaryText":"عبادت کر","isSecondaryTextArabic":false,"audioPath":"sabaq_20B_034.mp3"},{"arabic":"_a_عَابِد_\/a_","secondaryText":"عبادت کرنے والا","isSecondaryTextArabic":false,"audioPath":"sabaq_20B_035.mp3"},{"arabic":"_a_مَعْبُود_\/a_","secondaryText":"جس کی عبادت کی گئی","isSecondaryTextArabic":false,"audioPath":"sabaq_20B_036.mp3"},{"arabic":"_a_عِبَادَۃ_\/a_","secondaryText":"عبادت کرنا","isSecondaryTextArabic":false,"audioPath":"sabaq_20B_037.mp3"},{"arabic":"_a_ذَکَرَ_\/a_","secondaryText":"اس نے یاد کیا","isSecondaryTextArabic":false,"audioPath":"sabaq_20B_038.mp3"},{"arabic":"_a_یَذْکُرُ_\/a_","secondaryText":"وہ یاد کرتا ہے\/کرے گا","isSecondaryTextArabic":false,"audioPath":"sabaq_20B_039.mp3"},{"arabic":"_a_اُذْکُرْ_\/a_","secondaryText":"یاد کر","isSecondaryTextArabic":false,"audioPath":"sabaq_20B_040.mp3"},{"arabic":"_a_ذَاکِر_\/a_","secondaryText":"یاد کرنے والا","isSecondaryTextArabic":false,"audioPath":"sabaq_20B_041.mp3"},{"arabic":"_a_مَذْکُور_\/a_","secondaryText":"جس کو یاد کیا گیا","isSecondaryTextArabic":false,"audioPath":"sabaq_20B_042.mp3"},{"arabic":"_a_ذِکْر_\/a_","secondaryText":"یاد کرنا","isSecondaryTextArabic":false,"audioPath":"sabaq_20B_043.mp3"}]},{"header":{"text":"بَاب ضَرَبَ یَضْرِبُ اِضْرِبْ","audioPath":""},"rows":[{"arabic":"_a_ضَرَبَ_\/a_","secondaryText":"اس نے مارا","isSecondaryTextArabic":false,"audioPath":"sabaq_20B_044.mp3"},{"arabic":"_a_یَضْرِبَ_\/a_","secondaryText":"وہ مارتا ہے\/مارے گا","isSecondaryTextArabic":false,"audioPath":"sabaq_20B_045.mp3"},{"arabic":"_a_اِضْرِب_\/a_","secondaryText":"مار","isSecondaryTextArabic":false,"audioPath":"sabaq_20B_046.mp3"},{"arabic":"_a_ضَارِب_\/a_","secondaryText":"مارنے والا","isSecondaryTextArabic":false,"audioPath":"sabaq_20B_047.mp3"},{"arabic":"_a_مَضْرُوب_\/a_","secondaryText":"جس کو مارا گیا","isSecondaryTextArabic":false,"audioPath":"sabaq_20B_048.mp3"},{"arabic":"_a_ضَرْب_\/a_","secondaryText":"مارنا","isSecondaryTextArabic":false,"audioPath":"sabaq_20B_049.mp3"}]},{"header":{"text":"بَاب سَمِعَ یَسْمَعُ اِسْمَعْ","audioPath":""},"rows":[{"arabic":"_a_سَمِعَ_\/a_","secondaryText":"اس نے سنا","isSecondaryTextArabic":false,"audioPath":"sabaq_20B_050.mp3"},{"arabic":"_a_یَسْمَعُ_\/a_","secondaryText":"وہ سنتا ہے\/سنے گا","isSecondaryTextArabic":false,"audioPath":"sabaq_20B_051.mp3"},{"arabic":"_a_اِسْمَعْ_\/a_","secondaryText":"سن","isSecondaryTextArabic":false,"audioPath":"sabaq_20B_052.mp3"},{"arabic":"_a_سَامِع_\/a_","secondaryText":"سننے والا","isSecondaryTextArabic":false,"audioPath":"sabaq_20B_053.mp3"},{"arabic":"_a_مَسْمُوع_\/a_","secondaryText":"جس کو سنا گیا","isSecondaryTextArabic":false,"audioPath":"sabaq_20B_054.mp3"},{"arabic":"_a_سَمْع_\/a_","secondaryText":"سننا","isSecondaryTextArabic":false,"audioPath":"sabaq_20B_055.mp3"},{"arabic":"_a_عَلِمَ_\/a_","secondaryText":"اس نے جانا","isSecondaryTextArabic":false,"audioPath":"sabaq_20B_056.mp3"},{"arabic":"_a_یَعْلَمُ_\/a_","secondaryText":"وہ جانتا ہے\/جانے گا","isSecondaryTextArabic":false,"audioPath":"sabaq_20B_057.mp3"},{"arabic":"_a_اِعْلَمْ_\/a_","secondaryText":"جان","isSecondaryTextArabic":false,"audioPath":"sabaq_20B_058.mp3"},{"arabic":"_a_عَالِمْ_\/a_","secondaryText":"جاننے والا","isSecondaryTextArabic":false,"audioPath":"sabaq_20B_059.mp3"},{"arabic":"_a_مَعْلُوم_\/a_","secondaryText":"جس کو جانا گیا","isSecondaryTextArabic":false,"audioPath":"sabaq_20B_060.mp3"},{"arabic":"_a_عِلْمَ_\/a_","secondaryText":"جاننا","isSecondaryTextArabic":false,"audioPath":"sabaq_20B_061.mp3"},{"arabic":"_a_عَمِلَ_\/a_","secondaryText":"اس نے عمل کیا","isSecondaryTextArabic":false,"audioPath":"sabaq_20B_062.mp3"},{"arabic":"_a_یَعْمَلُ_\/a_","secondaryText":"وہ عمل کرتا ہے\/کرے گا","isSecondaryTextArabic":false,"audioPath":"sabaq_20B_063.mp3"},{"arabic":"_a_اِعْمَلْ_\/a_","secondaryText":"عمل کر","isSecondaryTextArabic":false,"audioPath":"sabaq_20B_064.mp3"},{"arabic":"_a_عَامِل_\/a_","secondaryText":"عمل کرنے والا","isSecondaryTextArabic":false,"audioPath":"sabaq_20B_065.mp3"},{"arabic":"_a_مَعْمُول_\/a_","secondaryText":"جس پر عمل کیا گیا","isSecondaryTextArabic":false,"audioPath":"sabaq_20B_066.mp3"},{"arabic":"_a_عَمَل_\/a_","secondaryText":"عمل کرنا","isSecondaryTextArabic":false,"audioPath":"sabaq_20B_067.mp3"}]},{"header":{"text":"_a_اَلْمُحَادَثَۃُ الْعَرَبِیَّۃ_\/a_ (عربی بول چال)\r\nنیچے دیے گئے جملے میں ’’آپ‘‘ اور ’’میں‘‘ کو آپس میں بدلنا ہے (یاد رکھیے _a_ہ، ھُمْ، کَ، کُمْ_\/a_…جڑے ہوئے ہیں مگر ان کو ذہن میں الگ کر کے دیکھیے اور تھوڑا وقفہ دے کر پڑھیے۔","audioPath":"sabaq_20B_068.mp3"},"rows":[{"arabic":"ھَلْ ضَرَبْتَہٗ؟ (ھَلْ ضَرَبْت ہٗ)","secondaryText":"مَا ضَرَبْتُہٗ (مَا ضَرَبْتُہٗ )","isSecondaryTextArabic":true,"audioPath":"sabaq_20B_069.mp3"},{"arabic":"ھَلْ نَصَرْتَہٗ (ھَلْ نَصَرْتَ ہٗ)","secondaryText":"مَا نَصَرْتُہٗ (مَا نَصَرْتُہٗ)","isSecondaryTextArabic":true,"audioPath":"sabaq_20B_070.mp3"},{"arabic":"ھَلْ ذَکَرْتَہٗ؟ (ھَلْ ذَکَرْتَ ہٗ)","secondaryText":"مَا ذَکَرْتُہٗ؟ (مَا ذَکَرْتُہٗ؟)","isSecondaryTextArabic":true,"audioPath":"sabaq_20B_071.mp3"},{"arabic":"ھَلْ ضَرَبْتُمُوْہٗ؟ (ھَلْ ضَرَبْتُمُوْہٗ)","secondaryText":"مَا ضَرَبْنَاہٗ (مَا ضَرَبْنَاہٗ)","isSecondaryTextArabic":true,"audioPath":"sabaq_20B_072.mp3"},{"arabic":"ھَلْ نَصَرْتُمُوْہٗ؟ (ھَلْ نَصَرْتُمُوْہٗ)","secondaryText":"مَا نَصَرْنَاہٗ (مَا نَصَرْنَاہٗ)","isSecondaryTextArabic":true,"audioPath":"sabaq_20B_073.mp3"},{"arabic":"ھَلْ ذَکَرْتُمُوْنَا؟ (ھَلْ ذَکَرْتُمُوْنَا)","secondaryText":"مَا ذَکَرْنَاکُمْ","isSecondaryTextArabic":true,"audioPath":"sabaq_20B_074.mp3"},{"arabic":"ھَلْ تَضْرَبُہٗ (ھَلْ تَضْرَبُہٗ)","secondaryText":"لَا أَضْرِبُہٗ (لَا أَضْرِبُہٗ)","isSecondaryTextArabic":true,"audioPath":"sabaq_20B_075.mp3"},{"arabic":"ھَلْ تَنْصُرُہٗ؟ (ھَلْ تَنْصُرُہٗ)","secondaryText":"لَا أَنْصُرُہٗ (لَا أَنْصُرُہٗ)","isSecondaryTextArabic":true,"audioPath":"sabaq_20B_076.mp3"},{"arabic":"ھَلْ تَذْکُرُہٗ؟ (ھَلْ تَذْکُرُہٗ)","secondaryText":"لَا أَذْکُرُہٗ (لَا أَذْکُرُہٗ)","isSecondaryTextArabic":true,"audioPath":"sabaq_20B_077.mp3"},{"arabic":"ھَلْ تَضْرِبُونَہٗ (ھَلْ تَضْرِبُونَہٗ)","secondaryText":"لَا نَضْرِبُہٗ (لَا نَضْرِبُہٗ)","isSecondaryTextArabic":true,"audioPath":"sabaq_20B_078.mp3"},{"arabic":"ھَلْ تَنْصُرُوْنَہٗ؟ (ھَلْ تَنْصُرُوْنَہٗ)","secondaryText":"لَا نَنْصُرُہٗ (لَا نَنْصُرُہٗ)","isSecondaryTextArabic":true,"audioPath":"sabaq_20B_079.mp3"},{"arabic":"ھَلْ تَذْکُرُوْنَہٗ؟ (ھَلْ تَذْکُرُوْنَہٗ)","secondaryText":"لَا نَذْکُرُہٗ (لَا نَذْکُرُہٗ)","isSecondaryTextArabic":true,"audioPath":"sabaq_20B_080.mp3"}]},{"header":{"text":"نیچے دیے گئے جملوں میں ’’آپ اور میں‘‘کو ’’میں اور آپ‘‘ سے بدلنا ہے۔ سارے سوالوں کا جواب نہ میں دیجیے (تاکہ نہ کی پریکٹس ہو!)","audioPath":""},"rows":[{"arabic":"ھَلْ ضَرَبْتَنِيْ؟ (ھَلْ ضَرَبْتَنِيْ)","secondaryText":"مَا ضَرَبْتُکَ","isSecondaryTextArabic":true,"audioPath":"sabaq_20B_082.mp3"},{"arabic":"ھَلْ نَصَرْتَنِيْ؟ (ھَلْ نَصَرْتَنِيْ)","secondaryText":"مَا نَصَرْتُکَ","isSecondaryTextArabic":true,"audioPath":"sabaq_20B_083.mp3"},{"arabic":"ھَلْ ذَکَرْتَنِيْ؟ (ھَلْ ذَکَرْتَنِيْ)","secondaryText":"مَا ذَکَرْتُکَ","isSecondaryTextArabic":true,"audioPath":"sabaq_20B_084.mp3"},{"arabic":"ھَلْ ضَرَبْتُمُونَا؟ (ھَلْ ضَرَبْتُمُونَا)","secondaryText":"مَا ضَرَبْنَاکُمْ","isSecondaryTextArabic":true,"audioPath":"sabaq_20B_085.mp3"},{"arabic":"ھَلْ نَصَرْتُمُونَا؟ (ھَلْ نَصَرْتُمُونَا)","secondaryText":"مَا نَصَرْنَاکُمْ","isSecondaryTextArabic":true,"audioPath":"sabaq_20B_086.mp3"},{"arabic":"ھَلْ ذَکَرْتُمُوْنَا؟ (ھَلْ ذَکَرْتُمُوْنَا)","secondaryText":"مَا ذَکَرْنَاکُمْ","isSecondaryTextArabic":true,"audioPath":"sabaq_20B_087.mp3"},{"arabic":"ھَلْ ضَرَبْتَنَا؟ (ھَلْ ضَرَبْتَنَا؟)","secondaryText":"مَا ضَرَبْتُکُمْ","isSecondaryTextArabic":true,"audioPath":"sabaq_20B_088.mp3"},{"arabic":"ھَلْ نَصَرْتَنَا؟ (ھَلْ نَصَرْتَنَا؟)","secondaryText":"مَا نَصَرْتُکُمْ","isSecondaryTextArabic":true,"audioPath":"sabaq_20B_089.mp3"},{"arabic":"ھَلْ ذَکَرْتَنَا؟ (ھَلْ ذَکَرْتَنَا؟)","secondaryText":"مَا ذَکَرْتُکُمْ","isSecondaryTextArabic":true,"audioPath":"sabaq_20B_090.mp3"},{"arabic":"ھَلْ ضَرَبْتُمُونَا؟ (ھَلْ ضَرَبْتُمُونَا؟)","secondaryText":"نَعَمْ! ضَرَبْنَاکُمْ","isSecondaryTextArabic":true,"audioPath":"sabaq_20B_091.mp3"},{"arabic":"ھَلْ سَمِعْتُمُونَا؟ (ھَلْ سَمِعْتُمُونَا؟)","secondaryText":"نَعَمَ! سَمِعْنَاکُمْ","isSecondaryTextArabic":true,"audioPath":"sabaq_20B_092.mp3"}]}],"lessonID":"020B"}